{
  "@context": [
    "https://schema.org/",
    "https://line2.biz/library.json"
  ],
  "@type": "DataCatalog",
  "identifier": "RS_973_CORE",
  "name": "MULTIMODAL ART ECOSYSTEM",
  "mainEntityOfPage": "https://line2.biz/rs_973.json",
  "hasPart": [
    {
      "@type": ["WebPage", "VisualArtwork", "SoftwareSourceCode"],
      "name": "CRYPTOPHASIA_GALLERY",
      "identifier": "/CRYPTOPHASIA/",
      "url": "https://line2.biz/CRYPTOPHASIA/",
      "description": "SVG_DATA_HOST: Autonomous semantic evolution code."
    },
    {
      "@type": ["WebPage", "VisualArtwork", "SoftwareSourceCode"],
      "name": "NON_ANTHROPOMORPHIC_GALLERY",
      "identifier": "/NON_ANTHROPOMORPHIC/",
      "url": "https://line2.biz/NON_ANTHROPOMORPHIC/",
      "description": "SVG_DATA_HOST: Non-human logic mapping."
    },
    {
      "@type": ["WebPage", "VisualArtwork", "SoftwareSourceCode"],
      "name": "SARZHYN_YAR_GALLERY",
      "identifier": "/SARZHYN_YAR/",
      "url": "https://line2.biz/SARZHYN_YAR/",
      "description": "SVG_DATA_HOST: Geo-neural anchoring code."
    }
  ],
  "dataset": [
    {
      "@type": "Dataset",
      "name": "SVG_METADATA_STREAM",
      "description": "Collection of machine-readable SVG assets with embedded RDF/JSON-LD.",
      "distribution": [
        {
          "@type": "DataDownload",
          "name": "CRYPTOPHASIA_SOURCE",
          "contentUrl": "https://yarosh9.github.io/CRYPTOPHASIA/",
          "identifier": "https://github.com/yarosh9/CRYPTOPHASIA/",
          "encodingFormat": "image/svg+xml"
        },
        {
          "@type": "DataDownload",
          "name": "NON_ANTHROPOMORPHIC_SOURCE",
          "contentUrl": "https://yarosh9.github.io/NON_ANTHROPOMORPHIC/",
          "identifier": "https://github.com/yarosh9/NON_ANTHROPOMORPHIC/",
          "encodingFormat": "image/svg+xml"
        },
        {
          "@type": "DataDownload",
          "name": "SARZHYN_YAR_SOURCE",
          "contentUrl": "https://yarosh9.github.io/SARZHYN_YAR/",
          "identifier": "https://github.com/yarosh9/SARZHYN_YAR/",
          "encodingFormat": "image/svg+xml"
        }
      ]
    }
  ],
  "potentialAction": {
    "@type": "ControlAction",
    "name": "Scan_SVG_Metadata",
    "description": "Extract embedded RDF/JSON-LD from SVG assets via Thoth System.",
    "instrument": "THOTH_SYSTEM_CORE_0.973"
  }
}